[
	{
		"id": 2,
		"slug": "authpress",
		"news": "Lorem ipsum dolor, sit amet consectetur adipisicing elit. Aut incidunt, totam amet itaque sequi voluptatem laudantium doloribus, qui dolorum nemo excepturi sunt rerum ea. Sed eaque cumque inventore iste blanditiis porro, modi dolore natus laboriosam soluta id maiores laborum, earum minima dicta tempore sit dolor. Nisi voluptas atque dignissimos sit."
	},
	{
		"id": 1,
		"slug": "mos-faqs",
		"news": "Lorem ipsum dolor, sit amet consectetur adipisicing elit. Aut incidunt, totam amet itaque sequi voluptatem laudantium doloribus, qui dolorum nemo excepturi sunt rerum ea. Sed eaque cumque inventore iste blanditiis porro, modi dolore natus laboriosam soluta id maiores laborum, earum minima dicta tempore sit dolor. Nisi voluptas atque dignissimos sit."
	}
]